{
  "id": "level-20",
  "slug": "level-20",
  "class": "dangereux",
  "danger": {
    "level": 5,
    "scale": 5,
    "tags": [
      "cold",
      "paranoia",
      "entity-infested",
      "hazardous-games"
    ]
  },
  "survival": {
    "safe": false,
    "secure": false,
    "entityCount": "eleve"
  },
  "entities": [
    {
      "id": "deathmoths",
      "presence": "occasional",
      "zones": []
    },
    {
      "id": "clumps",
      "presence": "occasional",
      "zones": []
    },
    {
      "id": "hounds",
      "presence": "frequent",
      "zones": []
    },
    {
      "id": "facelings",
      "presence": "occasional",
      "zones": []
    },
    {
      "id": "skin-stealers",
      "presence": "occasional",
      "zones": []
    }
  ],
  "connections": [
    {
      "to": "level-2",
      "type": "porte",
      "direction": "bidirectional",
      "method": {
        "en": "From this level's entrances/exits on the source wiki.",
        "fr": "D'après les entrées/sorties de ce niveau sur le wiki source."
      },
      "reliability": "inconnue"
    },
    {
      "to": "level-4",
      "type": "porte",
      "direction": "one-way",
      "method": {
        "en": "From this level's entrances/exits on the source wiki.",
        "fr": "D'après les entrées/sorties de ce niveau sur le wiki source."
      },
      "reliability": "inconnue"
    },
    {
      "to": "level-6",
      "type": "porte",
      "direction": "one-way",
      "method": {
        "en": "From this level's entrances/exits on the source wiki.",
        "fr": "D'après les entrées/sorties de ce niveau sur le wiki source."
      },
      "reliability": "inconnue"
    },
    {
      "to": "level-7",
      "type": "porte",
      "direction": "one-way",
      "method": {
        "en": "From this level's entrances/exits on the source wiki.",
        "fr": "D'après les entrées/sorties de ce niveau sur le wiki source."
      },
      "reliability": "inconnue"
    },
    {
      "to": "level-21",
      "type": "porte",
      "direction": "bidirectional",
      "method": {
        "en": "From this level's entrances/exits on the source wiki.",
        "fr": "D'après les entrées/sorties de ce niveau sur le wiki source."
      },
      "reliability": "inconnue"
    },
    {
      "to": "level-24",
      "type": "noclip",
      "direction": "one-way",
      "method": {
        "en": "From this level's entrances/exits on the source wiki.",
        "fr": "D'après les entrées/sorties de ce niveau sur le wiki source."
      },
      "reliability": "inconnue"
    },
    {
      "to": "level-36",
      "type": "porte",
      "direction": "one-way",
      "method": {
        "en": "From this level's entrances/exits on the source wiki.",
        "fr": "D'après les entrées/sorties de ce niveau sur le wiki source."
      },
      "reliability": "inconnue"
    }
  ],
  "i18n": {
    "en": {
      "name": "Level 20 — Boreas Structure",
      "shortDescription": "An amusement facility split into the Waiting Halls (lockers, vending) and the Electric (deadly game rooms), bitterly cold and paranoia-inducing.",
      "atmosphere": "Eerie artificially-lit amusement palace sinking into darkness and extreme cold, with breathing/wind hallucinations and phantom snow.",
      "tips": "Don't read expedition logs before entry. Use staff-only doors in the Waiting Halls to exit fast. Win games for supplies; losing teleports you."
    }
  },
  "media": {
    "thumbnail": "/images/levels/level-20-thumb.webp",
    "banner": "/images/levels/level-20-banner.webp"
  },
  "wikiUrl": {
    "en": "https://backrooms-wiki.wikidot.com/level-20",
    "fr": "https://backrooms-wiki.wikidot.com/level-20"
  },
  "layers": {
    "danger": true,
    "entities": true,
    "resources": false
  },
  "meta": {
    "addedOn": "2026-07-10",
    "status": "published",
    "source": "backrooms-wiki.wikidot.com"
  }
}
