{
  "id": "level-46",
  "slug": "level-46",
  "class": "dangereux",
  "danger": {
    "level": 4,
    "scale": 5,
    "tags": [
      "extreme-temperatures",
      "sandstorms",
      "ruins",
      "hostile-entities"
    ]
  },
  "survival": {
    "safe": false,
    "secure": false,
    "entityCount": "faible"
  },
  "entities": [
    {
      "id": "sand-spirits",
      "presence": "frequent",
      "zones": []
    }
  ],
  "connections": [
    {
      "to": "level-0",
      "type": "porte",
      "direction": "one-way",
      "method": {
        "en": "From this level's entrances/exits on the source wiki.",
        "fr": "D'après les entrées/sorties de ce niveau sur le wiki source."
      },
      "reliability": "inconnue"
    },
    {
      "to": "level-1",
      "type": "porte",
      "direction": "one-way",
      "method": {
        "en": "From this level's entrances/exits on the source wiki.",
        "fr": "D'après les entrées/sorties de ce niveau sur le wiki source."
      },
      "reliability": "inconnue"
    },
    {
      "to": "level-4",
      "type": "porte",
      "direction": "one-way",
      "method": {
        "en": "From this level's entrances/exits on the source wiki.",
        "fr": "D'après les entrées/sorties de ce niveau sur le wiki source."
      },
      "reliability": "inconnue"
    },
    {
      "to": "level-21",
      "type": "porte",
      "direction": "one-way",
      "method": {
        "en": "From this level's entrances/exits on the source wiki.",
        "fr": "D'après les entrées/sorties de ce niveau sur le wiki source."
      },
      "reliability": "inconnue"
    },
    {
      "to": "level-80",
      "type": "autre",
      "direction": "one-way",
      "method": {
        "en": "From this level's entrances/exits on the source wiki.",
        "fr": "D'après les entrées/sorties de ce niveau sur le wiki source."
      },
      "reliability": "inconnue"
    },
    {
      "to": "level-85",
      "type": "autre",
      "direction": "one-way",
      "method": {
        "en": "From this level's entrances/exits on the source wiki.",
        "fr": "D'après les entrées/sorties de ce niveau sur le wiki source."
      },
      "reliability": "inconnue"
    }
  ],
  "i18n": {
    "en": {
      "name": "Level 46 — Arabian Desert",
      "shortDescription": "A vast desert of scorching days and freezing nights, scattered with ancient ruins and prowled by hostile sand spirits.",
      "atmosphere": "Desolate and harsh, with violent climate swings and sandstorms that draw hostile entities out of the dunes.",
      "tips": "Shelter in ruins during temperature extremes. Avoid sandstorms or stay near oases. Carry water to fend off sand spirits."
    }
  },
  "media": {
    "thumbnail": "/images/levels/level-46-thumb.webp",
    "banner": "/images/levels/level-46-banner.webp"
  },
  "wikiUrl": {
    "en": "https://backrooms-wiki.wikidot.com/level-46",
    "fr": "https://backrooms-wiki.wikidot.com/level-46"
  },
  "layers": {
    "danger": true,
    "entities": true,
    "resources": false
  },
  "meta": {
    "addedOn": "2026-07-10",
    "status": "published",
    "source": "backrooms-wiki.wikidot.com"
  }
}
